README.md
bahamut/__init__.py
bahamut/client.py
bahamut/util.py
bahamut/view.py
bahamut/proto/__init__.py
bahamut_client-0.1.0.dist-info/METADATA
bahamut_client-0.1.0.dist-info/WHEEL
bahamut_client-0.1.0.dist-info/RECORD
